{"meta":{"app":"FFConverter ~ Joopie","format":"RGBA8888","image":"coralking_c18_tropicalfish.png","scale":"1.0","size":{"w":4096,"h":128},"version":"1.0"},"frames":{"coralking_c18_tropicalfish_coralking_c18_tropicalfish_64_a_0_107.png":{"frame":{"x":1479,"y":7,"w":26,"h":114},"sourceSize":{"w":26,"h":114},"spriteSourceSize":{"x":0,"y":0,"w":26,"h":114},"rotated":false,"trimmed":false},"coralking_c18_tropicalfish_coralking_c18_tropicalfish_64_a_0_132.png":{"frame":{"x":906,"y":7,"w":28,"h":114},"sourceSize":{"w":28,"h":114},"spriteSourceSize":{"x":0,"y":0,"w":28,"h":114},"rotated":false,"trimmed":false},"coralking_c18_tropicalfish_coralking_c18_tropicalfish_64_a_0_58.png":{"frame":{"x":305,"y":4,"w":28,"h":117},"sourceSize":{"w":28,"h":117},"spriteSourceSize":{"x":0,"y":0,"w":28,"h":117},"rotated":false,"trimmed":false},"coralking_c18_tropicalfish_coralking_c18_tropicalfish_64_a_0_83.png":{"frame":{"x":1954,"y":4,"w":23,"h":117},"sourceSize":{"w":23,"h":117},"spriteSourceSize":{"x":0,"y":0,"w":23,"h":117},"rotated":false,"trimmed":false},"coralking_c18_tropicalfish_coralking_c18_tropicalfish_64_a_0_15.png":{"frame":{"x":2410,"y":4,"w":21,"h":117},"sourceSize":{"w":21,"h":117},"spriteSourceSize":{"x":0,"y":0,"w":21,"h":117},"rotated":false,"trimmed":false},"coralking_c18_tropicalfish_coralking_c18_tropicalfish_64_a_0_23.png":{"frame":{"x":2191,"y":23,"w":28,"h":98},"sourceSize":{"w":28,"h":98},"spriteSourceSize":{"x":0,"y":0,"w":28,"h":98},"rotated":false,"trimmed":false},"coralking_c18_tropicalfish_coralking_c18_tropicalfish_64_a_0_124.png":{"frame":{"x":2078,"y":8,"w":23,"h":113},"sourceSize":{"w":23,"h":113},"spriteSourceSize":{"x":0,"y":0,"w":23,"h":113},"rotated":false,"trimmed":false},"coralking_c18_tropicalfish_coralking_c18_tropicalfish_64_a_0_31.png":{"frame":{"x":125,"y":4,"w":28,"h":117},"sourceSize":{"w":28,"h":117},"spriteSourceSize":{"x":0,"y":0,"w":28,"h":117},"rotated":false,"trimmed":false},"coralking_c18_tropicalfish_coralking_c18_tropicalfish_64_a_0_32.png":{"frame":{"x":395,"y":5,"w":28,"h":116},"sourceSize":{"w":28,"h":116},"spriteSourceSize":{"x":0,"y":0,"w":28,"h":116},"rotated":false,"trimmed":false},"coralking_c18_tropicalfish_coralking_c18_tropicalfish_64_a_0_49.png":{"frame":{"x":1723,"y":7,"w":26,"h":114},"sourceSize":{"w":26,"h":114},"spriteSourceSize":{"x":0,"y":0,"w":26,"h":114},"rotated":false,"trimmed":false},"coralking_c18_tropicalfish_coralking_c18_tropicalfish_64_a_0_75.png":{"frame":{"x":2131,"y":13,"w":28,"h":108},"sourceSize":{"w":28,"h":108},"spriteSourceSize":{"x":0,"y":0,"w":28,"h":108},"rotated":false,"trimmed":false},"coralking_c18_tropicalfish_coralking_c18_tropicalfish_64_a_0_7.png":{"frame":{"x":2311,"y":21,"w":26,"h":100},"sourceSize":{"w":26,"h":100},"spriteSourceSize":{"x":0,"y":0,"w":26,"h":100},"rotated":false,"trimmed":false},"coralking_c18_tropicalfish_coralking_c18_tropicalfish_64_a_0_66.png":{"frame":{"x":845,"y":7,"w":29,"h":114},"sourceSize":{"w":29,"h":114},"spriteSourceSize":{"x":0,"y":0,"w":29,"h":114},"rotated":false,"trimmed":false},"coralking_c18_tropicalfish_coralking_c18_tropicalfish_64_a_0_16.png":{"frame":{"x":2387,"y":5,"w":21,"h":116},"sourceSize":{"w":21,"h":116},"spriteSourceSize":{"x":0,"y":0,"w":21,"h":116},"rotated":false,"trimmed":false},"coralking_c18_tropicalfish_coralking_c18_tropicalfish_64_a_0_76.png":{"frame":{"x":2251,"y":24,"w":28,"h":97},"sourceSize":{"w":28,"h":97},"spriteSourceSize":{"x":0,"y":0,"w":28,"h":97},"rotated":false,"trimmed":false},"coralking_c18_tropicalfish_coralking_c18_tropicalfish_64_a_0_8.png":{"frame":{"x":2479,"y":31,"w":26,"h":90},"sourceSize":{"w":26,"h":90},"spriteSourceSize":{"x":0,"y":0,"w":26,"h":90},"rotated":false,"trimmed":false},"coralking_c18_tropicalfish_coralking_c18_tropicalfish_64_a_0_33.png":{"frame":{"x":65,"y":5,"w":28,"h":116},"sourceSize":{"w":28,"h":116},"spriteSourceSize":{"x":0,"y":0,"w":28,"h":116},"rotated":false,"trimmed":false},"coralking_c18_tropicalfish_coralking_c18_tropicalfish_64_a_0_122.png":{"frame":{"x":2053,"y":7,"w":23,"h":114},"sourceSize":{"w":23,"h":114},"spriteSourceSize":{"x":0,"y":0,"w":23,"h":114},"rotated":false,"trimmed":false},"coralking_c18_tropicalfish_coralking_c18_tropicalfish_64_a_0_84.png":{"frame":{"x":1904,"y":5,"w":23,"h":116},"sourceSize":{"w":23,"h":116},"spriteSourceSize":{"x":0,"y":0,"w":23,"h":116},"rotated":false,"trimmed":false},"coralking_c18_tropicalfish_coralking_c18_tropicalfish_64_a_0_93.png":{"frame":{"x":1854,"y":5,"w":23,"h":116},"sourceSize":{"w":23,"h":116},"spriteSourceSize":{"x":0,"y":0,"w":23,"h":116},"rotated":false,"trimmed":false},"coralking_c18_tropicalfish_coralking_c18_tropicalfish_64_a_0_24.png":{"frame":{"x":2221,"y":24,"w":28,"h":97},"sourceSize":{"w":28,"h":97},"spriteSourceSize":{"x":0,"y":0,"w":28,"h":97},"rotated":false,"trimmed":false},"coralking_c18_tropicalfish_coralking_c18_tropicalfish_64_a_0_117.png":{"frame":{"x":876,"y":7,"w":28,"h":114},"sourceSize":{"w":28,"h":114},"spriteSourceSize":{"x":0,"y":0,"w":28,"h":114},"rotated":false,"trimmed":false},"coralking_c18_tropicalfish_coralking_c18_tropicalfish_64_a_0_67.png":{"frame":{"x":1024,"y":6,"w":27,"h":115},"sourceSize":{"w":27,"h":115},"spriteSourceSize":{"x":0,"y":0,"w":27,"h":115},"rotated":false,"trimmed":false},"coralking_c18_tropicalfish_coralking_c18_tropicalfish_64_a_0_72.png":{"frame":{"x":665,"y":5,"w":28,"h":116},"sourceSize":{"w":28,"h":116},"spriteSourceSize":{"x":0,"y":0,"w":28,"h":116},"rotated":false,"trimmed":false},"coralking_c18_tropicalfish_coralking_c18_tropicalfish_64_a_0_135.png":{"frame":{"x":995,"y":6,"w":27,"h":115},"sourceSize":{"w":27,"h":115},"spriteSourceSize":{"x":0,"y":0,"w":27,"h":115},"rotated":false,"trimmed":false},"coralking_c18_tropicalfish_coralking_c18_tropicalfish_64_a_0_85.png":{"frame":{"x":1250,"y":3,"w":25,"h":118},"sourceSize":{"w":25,"h":118},"spriteSourceSize":{"x":0,"y":0,"w":25,"h":118},"rotated":false,"trimmed":false},"coralking_c18_tropicalfish_coralking_c18_tropicalfish_64_a_0_25.png":{"frame":{"x":215,"y":4,"w":28,"h":117},"sourceSize":{"w":28,"h":117},"spriteSourceSize":{"x":0,"y":0,"w":28,"h":117},"rotated":false,"trimmed":false},"coralking_c18_tropicalfish_coralking_c18_tropicalfish_64_a_0_86.png":{"frame":{"x":2,"y":2,"w":29,"h":119},"sourceSize":{"w":29,"h":119},"spriteSourceSize":{"x":0,"y":0,"w":29,"h":119},"rotated":false,"trimmed":false},"coralking_c18_tropicalfish_coralking_c18_tropicalfish_64_a_0_105.png":{"frame":{"x":1421,"y":7,"w":27,"h":114},"sourceSize":{"w":27,"h":114},"spriteSourceSize":{"x":0,"y":0,"w":27,"h":114},"rotated":false,"trimmed":false},"coralking_c18_tropicalfish_coralking_c18_tropicalfish_64_a_0_38.png":{"frame":{"x":455,"y":5,"w":28,"h":116},"sourceSize":{"w":28,"h":116},"spriteSourceSize":{"x":0,"y":0,"w":28,"h":116},"rotated":false,"trimmed":false},"coralking_c18_tropicalfish_coralking_c18_tropicalfish_64_a_0_5.png":{"frame":{"x":1110,"y":5,"w":26,"h":116},"sourceSize":{"w":26,"h":116},"spriteSourceSize":{"x":0,"y":0,"w":26,"h":116},"rotated":false,"trimmed":false},"coralking_c18_tropicalfish_coralking_c18_tropicalfish_64_a_0_119.png":{"frame":{"x":1829,"y":6,"w":23,"h":115},"sourceSize":{"w":23,"h":115},"spriteSourceSize":{"x":0,"y":0,"w":23,"h":115},"rotated":false,"trimmed":false},"coralking_c18_tropicalfish_coralking_c18_tropicalfish_64_a_0_90.png":{"frame":{"x":1751,"y":7,"w":25,"h":114},"sourceSize":{"w":25,"h":114},"spriteSourceSize":{"x":0,"y":0,"w":25,"h":114},"rotated":false,"trimmed":false},"coralking_c18_tropicalfish_coralking_c18_tropicalfish_64_a_0_106.png":{"frame":{"x":1450,"y":7,"w":27,"h":114},"sourceSize":{"w":27,"h":114},"spriteSourceSize":{"x":0,"y":0,"w":27,"h":114},"rotated":false,"trimmed":false},"coralking_c18_tropicalfish_coralking_c18_tropicalfish_64_a_0_57.png":{"frame":{"x":275,"y":4,"w":28,"h":117},"sourceSize":{"w":28,"h":117},"spriteSourceSize":{"x":0,"y":0,"w":28,"h":117},"rotated":false,"trimmed":false},"coralking_c18_tropicalfish_coralking_c18_tropicalfish_64_a_0_30.png":{"frame":{"x":155,"y":4,"w":28,"h":117},"sourceSize":{"w":28,"h":117},"spriteSourceSize":{"x":0,"y":0,"w":28,"h":117},"rotated":false,"trimmed":false},"coralking_c18_tropicalfish_coralking_c18_tropicalfish_64_a_0_73.png":{"frame":{"x":815,"y":6,"w":28,"h":115},"sourceSize":{"w":28,"h":115},"spriteSourceSize":{"x":0,"y":0,"w":28,"h":115},"rotated":false,"trimmed":false},"coralking_c18_tropicalfish_coralking_c18_tropicalfish_64_a_0_87.png":{"frame":{"x":2363,"y":5,"w":22,"h":116},"sourceSize":{"w":22,"h":116},"spriteSourceSize":{"x":0,"y":0,"w":22,"h":116},"rotated":false,"trimmed":false},"coralking_c18_tropicalfish_coralking_c18_tropicalfish_64_a_0_136.png":{"frame":{"x":1305,"y":5,"w":26,"h":116},"sourceSize":{"w":26,"h":116},"spriteSourceSize":{"x":0,"y":0,"w":26,"h":116},"rotated":false,"trimmed":false},"coralking_c18_tropicalfish_coralking_c18_tropicalfish_64_a_0_6.png":{"frame":{"x":2103,"y":11,"w":26,"h":110},"sourceSize":{"w":26,"h":110},"spriteSourceSize":{"x":0,"y":0,"w":26,"h":110},"rotated":false,"trimmed":false},"coralking_c18_tropicalfish_coralking_c18_tropicalfish_64_a_0_43.png":{"frame":{"x":365,"y":4,"w":28,"h":117},"sourceSize":{"w":28,"h":117},"spriteSourceSize":{"x":0,"y":0,"w":28,"h":117},"rotated":false,"trimmed":false},"coralking_c18_tropicalfish_coralking_c18_tropicalfish_icon_a.png":{"frame":{"x":2479,"y":2,"w":26,"h":27},"sourceSize":{"w":26,"h":27},"spriteSourceSize":{"x":0,"y":0,"w":26,"h":27},"rotated":false,"trimmed":false},"coralking_c18_tropicalfish_coralking_c18_tropicalfish_64_a_0_39.png":{"frame":{"x":425,"y":5,"w":28,"h":116},"sourceSize":{"w":28,"h":116},"spriteSourceSize":{"x":0,"y":0,"w":28,"h":116},"rotated":false,"trimmed":false},"coralking_c18_tropicalfish_coralking_c18_tropicalfish_64_a_0_26.png":{"frame":{"x":33,"y":5,"w":30,"h":116},"sourceSize":{"w":30,"h":116},"spriteSourceSize":{"x":0,"y":0,"w":30,"h":116},"rotated":false,"trimmed":false},"coralking_c18_tropicalfish_coralking_c18_tropicalfish_64_a_0_28.png":{"frame":{"x":605,"y":5,"w":28,"h":116},"sourceSize":{"w":28,"h":116},"spriteSourceSize":{"x":0,"y":0,"w":28,"h":116},"rotated":false,"trimmed":false},"coralking_c18_tropicalfish_coralking_c18_tropicalfish_64_a_0_10.png":{"frame":{"x":2535,"y":36,"w":26,"h":85},"sourceSize":{"w":26,"h":85},"spriteSourceSize":{"x":0,"y":0,"w":26,"h":85},"rotated":false,"trimmed":false},"coralking_c18_tropicalfish_coralking_c18_tropicalfish_64_a_0_70.png":{"frame":{"x":635,"y":5,"w":28,"h":116},"sourceSize":{"w":28,"h":116},"spriteSourceSize":{"x":0,"y":0,"w":28,"h":116},"rotated":false,"trimmed":false},"coralking_c18_tropicalfish_coralking_c18_tropicalfish_64_a_0_88.png":{"frame":{"x":1618,"y":6,"w":25,"h":115},"sourceSize":{"w":25,"h":115},"spriteSourceSize":{"x":0,"y":0,"w":25,"h":115},"rotated":false,"trimmed":false},"coralking_c18_tropicalfish_coralking_c18_tropicalfish_64_a_0_137.png":{"frame":{"x":1194,"y":4,"w":26,"h":117},"sourceSize":{"w":26,"h":117},"spriteSourceSize":{"x":0,"y":0,"w":26,"h":117},"rotated":false,"trimmed":false},"coralking_c18_tropicalfish_coralking_c18_tropicalfish_64_a_0_62.png":{"frame":{"x":1645,"y":4,"w":25,"h":117},"sourceSize":{"w":25,"h":117},"spriteSourceSize":{"x":0,"y":0,"w":25,"h":117},"rotated":false,"trimmed":false},"coralking_c18_tropicalfish_coralking_c18_tropicalfish_64_a_0_36.png":{"frame":{"x":485,"y":5,"w":28,"h":116},"sourceSize":{"w":28,"h":116},"spriteSourceSize":{"x":0,"y":0,"w":28,"h":116},"rotated":false,"trimmed":false},"coralking_c18_tropicalfish_coralking_c18_tropicalfish_64_a_0_103.png":{"frame":{"x":1333,"y":6,"w":26,"h":115},"sourceSize":{"w":26,"h":115},"spriteSourceSize":{"x":0,"y":0,"w":26,"h":115},"rotated":false,"trimmed":false},"coralking_c18_tropicalfish_coralking_c18_tropicalfish_64_a_0_1.png":{"frame":{"x":1277,"y":5,"w":26,"h":116},"sourceSize":{"w":26,"h":116},"spriteSourceSize":{"x":0,"y":0,"w":26,"h":116},"rotated":false,"trimmed":false},"coralking_c18_tropicalfish_coralking_c18_tropicalfish_64_a_0_101.png":{"frame":{"x":545,"y":5,"w":28,"h":116},"sourceSize":{"w":28,"h":116},"spriteSourceSize":{"x":0,"y":0,"w":28,"h":116},"rotated":false,"trimmed":false},"coralking_c18_tropicalfish_coralking_c18_tropicalfish_64_a_0_129.png":{"frame":{"x":1778,"y":7,"w":24,"h":114},"sourceSize":{"w":24,"h":114},"spriteSourceSize":{"x":0,"y":0,"w":24,"h":114},"rotated":false,"trimmed":false},"coralking_c18_tropicalfish_coralking_c18_tropicalfish_64_a_0_3.png":{"frame":{"x":2433,"y":3,"w":21,"h":118},"sourceSize":{"w":21,"h":118},"spriteSourceSize":{"x":0,"y":0,"w":21,"h":118},"rotated":false,"trimmed":false},"coralking_c18_tropicalfish_coralking_c18_tropicalfish_64_a_0_46.png":{"frame":{"x":695,"y":5,"w":28,"h":116},"sourceSize":{"w":28,"h":116},"spriteSourceSize":{"x":0,"y":0,"w":28,"h":116},"rotated":false,"trimmed":false},"coralking_c18_tropicalfish_coralking_c18_tropicalfish_64_a_0_71.png":{"frame":{"x":785,"y":6,"w":28,"h":115},"sourceSize":{"w":28,"h":115},"spriteSourceSize":{"x":0,"y":0,"w":28,"h":115},"rotated":false,"trimmed":false},"coralking_c18_tropicalfish_coralking_c18_tropicalfish_64_a_0_0.png":{"frame":{"x":1166,"y":4,"w":26,"h":117},"sourceSize":{"w":26,"h":117},"spriteSourceSize":{"x":0,"y":0,"w":26,"h":117},"rotated":false,"trimmed":false},"coralking_c18_tropicalfish_coralking_c18_tropicalfish_64_a_0_37.png":{"frame":{"x":185,"y":4,"w":28,"h":117},"sourceSize":{"w":28,"h":117},"spriteSourceSize":{"x":0,"y":0,"w":28,"h":117},"rotated":false,"trimmed":false},"coralking_c18_tropicalfish_coralking_c18_tropicalfish_64_a_0_104.png":{"frame":{"x":966,"y":6,"w":27,"h":115},"sourceSize":{"w":27,"h":115},"spriteSourceSize":{"x":0,"y":0,"w":27,"h":115},"rotated":false,"trimmed":false},"coralking_c18_tropicalfish_coralking_c18_tropicalfish_64_a_0_19.png":{"frame":{"x":245,"y":4,"w":28,"h":117},"sourceSize":{"w":28,"h":117},"spriteSourceSize":{"x":0,"y":0,"w":28,"h":117},"rotated":false,"trimmed":false},"coralking_c18_tropicalfish_coralking_c18_tropicalfish_64_a_0_20.png":{"frame":{"x":575,"y":5,"w":28,"h":116},"sourceSize":{"w":28,"h":116},"spriteSourceSize":{"x":0,"y":0,"w":28,"h":116},"rotated":false,"trimmed":false},"coralking_c18_tropicalfish_coralking_c18_tropicalfish_64_a_0_100.png":{"frame":{"x":1804,"y":6,"w":23,"h":115},"sourceSize":{"w":23,"h":115},"spriteSourceSize":{"x":0,"y":0,"w":23,"h":115},"rotated":false,"trimmed":false},"coralking_c18_tropicalfish_coralking_c18_tropicalfish_64_a_0_54.png":{"frame":{"x":335,"y":4,"w":28,"h":117},"sourceSize":{"w":28,"h":117},"spriteSourceSize":{"x":0,"y":0,"w":28,"h":117},"rotated":false,"trimmed":false},"coralking_c18_tropicalfish_coralking_c18_tropicalfish_64_a_0_63.png":{"frame":{"x":1053,"y":5,"w":27,"h":116},"sourceSize":{"w":27,"h":116},"spriteSourceSize":{"x":0,"y":0,"w":27,"h":116},"rotated":false,"trimmed":false},"coralking_c18_tropicalfish_coralking_c18_tropicalfish_64_a_0_4.png":{"frame":{"x":1138,"y":4,"w":26,"h":117},"sourceSize":{"w":26,"h":117},"spriteSourceSize":{"x":0,"y":0,"w":26,"h":117},"rotated":false,"trimmed":false},"coralking_c18_tropicalfish_coralking_c18_tropicalfish_64_a_0_77.png":{"frame":{"x":2281,"y":25,"w":28,"h":96},"sourceSize":{"w":28,"h":96},"spriteSourceSize":{"x":0,"y":0,"w":28,"h":96},"rotated":false,"trimmed":false},"coralking_c18_tropicalfish_coralking_c18_tropicalfish_64_a_0_34.png":{"frame":{"x":95,"y":4,"w":28,"h":117},"sourceSize":{"w":28,"h":117},"spriteSourceSize":{"x":0,"y":0,"w":28,"h":117},"rotated":false,"trimmed":false},"coralking_c18_tropicalfish_coralking_c18_tropicalfish_64_a_0_113.png":{"frame":{"x":1507,"y":7,"w":26,"h":114},"sourceSize":{"w":26,"h":114},"spriteSourceSize":{"x":0,"y":0,"w":26,"h":114},"rotated":false,"trimmed":false},"coralking_c18_tropicalfish_coralking_c18_tropicalfish_64_a_0_9.png":{"frame":{"x":2507,"y":35,"w":26,"h":86},"sourceSize":{"w":26,"h":86},"spriteSourceSize":{"x":0,"y":0,"w":26,"h":86},"rotated":false,"trimmed":false},"coralking_c18_tropicalfish_coralking_c18_tropicalfish_64_a_0_126.png":{"frame":{"x":2003,"y":6,"w":23,"h":115},"sourceSize":{"w":23,"h":115},"spriteSourceSize":{"x":0,"y":0,"w":23,"h":115},"rotated":false,"trimmed":false},"coralking_c18_tropicalfish_coralking_c18_tropicalfish_64_a_0_17.png":{"frame":{"x":1672,"y":4,"w":23,"h":117},"sourceSize":{"w":23,"h":117},"spriteSourceSize":{"x":0,"y":0,"w":23,"h":117},"rotated":false,"trimmed":false},"coralking_c18_tropicalfish_coralking_c18_tropicalfish_64_a_0_21.png":{"frame":{"x":1391,"y":9,"w":28,"h":112},"sourceSize":{"w":28,"h":112},"spriteSourceSize":{"x":0,"y":0,"w":28,"h":112},"rotated":false,"trimmed":false},"coralking_c18_tropicalfish_coralking_c18_tropicalfish_64_a_0_109.png":{"frame":{"x":1361,"y":8,"w":28,"h":113},"sourceSize":{"w":28,"h":113},"spriteSourceSize":{"x":0,"y":0,"w":28,"h":113},"rotated":false,"trimmed":false},"coralking_c18_tropicalfish_coralking_c18_tropicalfish_64_a_0_134.png":{"frame":{"x":755,"y":6,"w":28,"h":115},"sourceSize":{"w":28,"h":115},"spriteSourceSize":{"x":0,"y":0,"w":28,"h":115},"rotated":false,"trimmed":false},"coralking_c18_tropicalfish_coralking_c18_tropicalfish_64_a_0_47.png":{"frame":{"x":936,"y":6,"w":28,"h":115},"sourceSize":{"w":28,"h":115},"spriteSourceSize":{"x":0,"y":0,"w":28,"h":115},"rotated":false,"trimmed":false},"coralking_c18_tropicalfish_coralking_c18_tropicalfish_64_a_0_121.png":{"frame":{"x":1082,"y":5,"w":26,"h":116},"sourceSize":{"w":26,"h":116},"spriteSourceSize":{"x":0,"y":0,"w":26,"h":116},"rotated":false,"trimmed":false},"coralking_c18_tropicalfish_coralking_c18_tropicalfish_64_a_0_18.png":{"frame":{"x":1879,"y":5,"w":23,"h":116},"sourceSize":{"w":23,"h":116},"spriteSourceSize":{"x":0,"y":0,"w":23,"h":116},"rotated":false,"trimmed":false},"coralking_c18_tropicalfish_coralking_c18_tropicalfish_64_a_0_127.png":{"frame":{"x":2028,"y":6,"w":23,"h":115},"sourceSize":{"w":23,"h":115},"spriteSourceSize":{"x":0,"y":0,"w":23,"h":115},"rotated":false,"trimmed":false},"coralking_c18_tropicalfish_coralking_c18_tropicalfish_64_a_0_64.png":{"frame":{"x":1222,"y":3,"w":26,"h":118},"sourceSize":{"w":26,"h":118},"spriteSourceSize":{"x":0,"y":0,"w":26,"h":118},"rotated":false,"trimmed":false},"coralking_c18_tropicalfish_coralking_c18_tropicalfish_64_a_0_120.png":{"frame":{"x":1697,"y":5,"w":24,"h":116},"sourceSize":{"w":24,"h":116},"spriteSourceSize":{"x":0,"y":0,"w":24,"h":116},"rotated":false,"trimmed":false},"coralking_c18_tropicalfish_coralking_c18_tropicalfish_64_a_0_35.png":{"frame":{"x":515,"y":5,"w":28,"h":116},"sourceSize":{"w":28,"h":116},"spriteSourceSize":{"x":0,"y":0,"w":28,"h":116},"rotated":false,"trimmed":false},"coralking_c18_tropicalfish_coralking_c18_tropicalfish_64_a_0_22.png":{"frame":{"x":2161,"y":19,"w":28,"h":102},"sourceSize":{"w":28,"h":102},"spriteSourceSize":{"x":0,"y":0,"w":28,"h":102},"rotated":false,"trimmed":false},"coralking_c18_tropicalfish_coralking_c18_tropicalfish_64_a_0_95.png":{"frame":{"x":1979,"y":5,"w":22,"h":116},"sourceSize":{"w":22,"h":116},"spriteSourceSize":{"x":0,"y":0,"w":22,"h":116},"rotated":false,"trimmed":false},"coralking_c18_tropicalfish_coralking_c18_tropicalfish_64_a_0_82.png":{"frame":{"x":1929,"y":5,"w":23,"h":116},"sourceSize":{"w":23,"h":116},"spriteSourceSize":{"x":0,"y":0,"w":23,"h":116},"rotated":false,"trimmed":false},"coralking_c18_tropicalfish_coralking_c18_tropicalfish_64_a_0_48.png":{"frame":{"x":1563,"y":6,"w":26,"h":115},"sourceSize":{"w":26,"h":115},"spriteSourceSize":{"x":0,"y":0,"w":26,"h":115},"rotated":false,"trimmed":false},"coralking_c18_tropicalfish_coralking_c18_tropicalfish_64_a_0_128.png":{"frame":{"x":2339,"y":5,"w":22,"h":116},"sourceSize":{"w":22,"h":116},"spriteSourceSize":{"x":0,"y":0,"w":22,"h":116},"rotated":false,"trimmed":false},"coralking_c18_tropicalfish_coralking_c18_tropicalfish_64_a_0_115.png":{"frame":{"x":1591,"y":6,"w":25,"h":115},"sourceSize":{"w":25,"h":115},"spriteSourceSize":{"x":0,"y":0,"w":25,"h":115},"rotated":false,"trimmed":false},"coralking_c18_tropicalfish_coralking_c18_tropicalfish_64_a_0_2.png":{"frame":{"x":2456,"y":2,"w":21,"h":119},"sourceSize":{"w":21,"h":119},"spriteSourceSize":{"x":0,"y":0,"w":21,"h":119},"rotated":false,"trimmed":false},"coralking_c18_tropicalfish_coralking_c18_tropicalfish_64_a_0_102.png":{"frame":{"x":725,"y":6,"w":28,"h":115},"sourceSize":{"w":28,"h":115},"spriteSourceSize":{"x":0,"y":0,"w":28,"h":115},"rotated":false,"trimmed":false},"coralking_c18_tropicalfish_coralking_c18_tropicalfish_64_a_0_52.png":{"frame":{"x":1535,"y":6,"w":26,"h":115},"sourceSize":{"w":26,"h":115},"spriteSourceSize":{"x":0,"y":0,"w":26,"h":115},"rotated":false,"trimmed":false}}}