{"meta":{"app":"FFConverter ~ Joopie","format":"RGBA8888","image":"xm09_bauble_18.png","scale":"1.0","size":{"w":64,"h":64},"version":"1.0"},"frames":{"xm09_bauble_18_xm09_bauble_18_icon_a.png":{"frame":{"x":18,"y":14,"w":14,"h":30},"sourceSize":{"w":14,"h":30},"spriteSourceSize":{"x":0,"y":0,"w":14,"h":30},"rotated":false,"trimmed":false},"xm09_bauble_18_xm09_bauble_18_64_b_2_0.png":{"frame":{"x":2,"y":2,"w":14,"h":42},"sourceSize":{"w":14,"h":42},"spriteSourceSize":{"x":0,"y":0,"w":14,"h":42},"rotated":false,"trimmed":false},"xm09_bauble_18_xm09_bauble_18_64_a_2_0.png":{"frame":{"x":34,"y":22,"w":10,"h":22},"sourceSize":{"w":10,"h":22},"spriteSourceSize":{"x":0,"y":0,"w":10,"h":22},"rotated":false,"trimmed":false}}}