{"type":"furniture","name":"arabian_wall","visualizationType":"furniture_animated","logicType":"furniture_multistate","spritesheet":"arabian_wall_spritesheet.json","dimensions":{"x":1.9375,"y":0.2,"z":3.25},"directions":[90,180],"assets":{"arabian_wall_64_a_2_0":{"x":31,"y":67},"arabian_wall_64_b_2_0":{"x":34,"y":108},"arabian_wall_64_b_4_0":{"source":"arabian_wall_64_b_2_0","x":34,"y":108,"flipH":true},"arabian_wall_64_b_2_1":{"x":34,"y":108},"arabian_wall_icon_a":{"x":6,"y":16},"arabian_wall_64_a_4_0":{"source":"arabian_wall_64_a_2_0","x":31,"y":67,"flipH":true},"arabian_wall_64_b_4_1":{"source":"arabian_wall_64_b_2_1","x":34,"y":108,"flipH":true}},"visualization":{"layerCount":2,"angle":45,"layers":{"0":{"z":-1900.0},"1":{"z":-3000.0}},"directions":{"2":{},"4":{}},"animations":{"0":{"layers":{"0":{"frameSequences":{"0":{"frames":{"0":{"id":0}}}}},"1":{"frameSequences":{"0":{"frames":{"0":{"id":0}}}}}}},"1":{"layers":{"1":{"frameSequences":{"0":{"frames":{"0":{"id":1}}}}}}}}}}