{"meta":{"app":"FFConverter ~ Joopie","format":"RGBA8888","image":"hween13_bridgemid.png","scale":"1.0","size":{"w":256,"h":256},"version":"1.0"},"frames":{"hween13_bridgemid_hween13_bridgemid_64_a_0_10.png":{"frame":{"x":2,"y":146,"w":64,"h":108},"sourceSize":{"w":64,"h":108},"spriteSourceSize":{"x":0,"y":0,"w":64,"h":108},"rotated":false,"trimmed":false},"hween13_bridgemid_hween13_bridgemid_64_a_0_7.png":{"frame":{"x":119,"y":162,"w":49,"h":92},"sourceSize":{"w":49,"h":92},"spriteSourceSize":{"x":0,"y":0,"w":49,"h":92},"rotated":false,"trimmed":false},"hween13_bridgemid_hween13_bridgemid_64_a_0_4.png":{"frame":{"x":190,"y":96,"w":46,"h":75},"sourceSize":{"w":46,"h":75},"spriteSourceSize":{"x":0,"y":0,"w":46,"h":75},"rotated":false,"trimmed":false},"hween13_bridgemid_hween13_bridgemid_64_a_0_2.png":{"frame":{"x":101,"y":76,"w":36,"h":75},"sourceSize":{"w":36,"h":75},"spriteSourceSize":{"x":0,"y":0,"w":36,"h":75},"rotated":false,"trimmed":false},"hween13_bridgemid_hween13_bridgemid_64_b_0_7.png":{"frame":{"x":60,"y":2,"w":36,"h":65},"sourceSize":{"w":36,"h":65},"spriteSourceSize":{"x":0,"y":0,"w":36,"h":65},"rotated":false,"trimmed":false},"hween13_bridgemid_hween13_bridgemid_64_b_0_1.png":{"frame":{"x":98,"y":2,"w":36,"h":65},"sourceSize":{"w":36,"h":65},"spriteSourceSize":{"x":0,"y":0,"w":36,"h":65},"rotated":false,"trimmed":false},"hween13_bridgemid_hween13_bridgemid_64_a_0_6.png":{"frame":{"x":170,"y":173,"w":49,"h":81},"sourceSize":{"w":49,"h":81},"spriteSourceSize":{"x":0,"y":0,"w":49,"h":81},"rotated":false,"trimmed":false},"hween13_bridgemid_hween13_bridgemid_64_a_0_8.png":{"frame":{"x":68,"y":153,"w":49,"h":101},"sourceSize":{"w":49,"h":101},"spriteSourceSize":{"x":0,"y":0,"w":49,"h":101},"rotated":false,"trimmed":false},"hween13_bridgemid_hween13_bridgemid_64_a_0_3.png":{"frame":{"x":60,"y":69,"w":39,"h":75},"sourceSize":{"w":39,"h":75},"spriteSourceSize":{"x":0,"y":0,"w":39,"h":75},"rotated":false,"trimmed":false},"hween13_bridgemid_hween13_bridgemid_64_a_0_5.png":{"frame":{"x":139,"y":85,"w":49,"h":75},"sourceSize":{"w":49,"h":75},"spriteSourceSize":{"x":0,"y":0,"w":49,"h":75},"rotated":false,"trimmed":false},"hween13_bridgemid_hween13_bridgemid_64_a_0_9.png":{"frame":{"x":2,"y":39,"w":56,"h":105},"sourceSize":{"w":56,"h":105},"spriteSourceSize":{"x":0,"y":0,"w":56,"h":105},"rotated":false,"trimmed":false},"hween13_bridgemid_hween13_bridgemid_64_b_0_2.png":{"frame":{"x":136,"y":9,"w":36,"h":65},"sourceSize":{"w":36,"h":65},"spriteSourceSize":{"x":0,"y":0,"w":36,"h":65},"rotated":false,"trimmed":false},"hween13_bridgemid_hween13_bridgemid_icon_a.png":{"frame":{"x":2,"y":7,"w":25,"h":30},"sourceSize":{"w":25,"h":30},"spriteSourceSize":{"x":0,"y":0,"w":25,"h":30},"rotated":false,"trimmed":false}}}