{"meta":{"app":"FFConverter ~ Joopie","format":"RGBA8888","image":"cine_soda.png","scale":"1.0","size":{"w":256,"h":256},"version":"1.0"},"frames":{"cine_soda_cine_soda_64_a_4_0.png":{"frame":{"x":65,"y":83,"w":64,"h":126},"sourceSize":{"w":64,"h":126},"spriteSourceSize":{"x":0,"y":0,"w":64,"h":126},"rotated":false,"trimmed":false},"cine_soda_cine_soda_64_sd_6_0.png":{"frame":{"x":65,"y":74,"w":36,"h":7},"sourceSize":{"w":36,"h":7},"spriteSourceSize":{"x":0,"y":0,"w":36,"h":7},"rotated":false,"trimmed":false},"cine_soda_cine_soda_64_a_0_0.png":{"frame":{"x":2,"y":80,"w":61,"h":129},"sourceSize":{"w":61,"h":129},"spriteSourceSize":{"x":0,"y":0,"w":61,"h":129},"rotated":false,"trimmed":false},"cine_soda_cine_soda_64_a_2_0.png":{"frame":{"x":131,"y":82,"w":60,"h":127},"sourceSize":{"w":60,"h":127},"spriteSourceSize":{"x":0,"y":0,"w":60,"h":127},"rotated":false,"trimmed":false},"cine_soda_cine_soda_64_sd_4_0.png":{"frame":{"x":2,"y":62,"w":52,"h":16},"sourceSize":{"w":52,"h":16},"spriteSourceSize":{"x":0,"y":0,"w":52,"h":16},"rotated":false,"trimmed":false},"cine_soda_cine_soda_64_a_6_0.png":{"frame":{"x":193,"y":80,"w":60,"h":129},"sourceSize":{"w":60,"h":129},"spriteSourceSize":{"x":0,"y":0,"w":60,"h":129},"rotated":false,"trimmed":false},"cine_soda_cine_soda_64_sd_2_0.png":{"frame":{"x":2,"y":45,"w":46,"h":15},"sourceSize":{"w":46,"h":15},"spriteSourceSize":{"x":0,"y":0,"w":46,"h":15},"rotated":false,"trimmed":false},"cine_soda_cine_soda_64_sd_0_0.png":{"frame":{"x":2,"y":33,"w":49,"h":10},"sourceSize":{"w":49,"h":10},"spriteSourceSize":{"x":0,"y":0,"w":49,"h":10},"rotated":false,"trimmed":false},"cine_soda_cine_soda_icon_a.png":{"frame":{"x":2,"y":2,"w":17,"h":29},"sourceSize":{"w":17,"h":29},"spriteSourceSize":{"x":0,"y":0,"w":17,"h":29},"rotated":false,"trimmed":false}}}