{"meta":{"app":"FFConverter ~ Joopie","format":"RGBA8888","image":"cine_bigcorn.png","scale":"1.0","size":{"w":64,"h":256},"version":"1.0"},"frames":{"cine_bigcorn_cine_bigcorn_64_a_2_0.png":{"frame":{"x":2,"y":124,"w":58,"h":88},"sourceSize":{"w":58,"h":88},"spriteSourceSize":{"x":0,"y":0,"w":58,"h":88},"rotated":false,"trimmed":false},"cine_bigcorn_cine_bigcorn_64_sd_2_0.png":{"frame":{"x":2,"y":13,"w":38,"h":19},"sourceSize":{"w":38,"h":19},"spriteSourceSize":{"x":0,"y":0,"w":38,"h":19},"rotated":false,"trimmed":false},"cine_bigcorn_cine_bigcorn_icon_a.png":{"frame":{"x":42,"y":2,"w":20,"h":30},"sourceSize":{"w":20,"h":30},"spriteSourceSize":{"x":0,"y":0,"w":20,"h":30},"rotated":false,"trimmed":false},"cine_bigcorn_cine_bigcorn_64_a_0_0.png":{"frame":{"x":2,"y":34,"w":58,"h":88},"sourceSize":{"w":58,"h":88},"spriteSourceSize":{"x":0,"y":0,"w":58,"h":88},"rotated":false,"trimmed":false}}}