{"meta":{"app":"FFConverter ~ Joopie","format":"RGBA8888","image":"pirate_mast_g.png","scale":"1.0","size":{"w":1024,"h":1024},"version":"1.0"},"frames":{"pirate_mast_g_pirate_mast_g_64_d_0_0.png":{"frame":{"x":218,"y":179,"w":36,"h":313},"sourceSize":{"w":36,"h":313},"spriteSourceSize":{"x":0,"y":0,"w":36,"h":313},"rotated":false,"trimmed":false},"pirate_mast_g_pirate_mast_g_icon_a.png":{"frame":{"x":292,"y":404,"w":13,"h":29},"sourceSize":{"w":13,"h":29},"spriteSourceSize":{"x":0,"y":0,"w":13,"h":29},"rotated":false,"trimmed":false},"pirate_mast_g_pirate_mast_g_64_k_0_3.png":{"frame":{"x":648,"y":26,"w":70,"h":118},"sourceSize":{"w":70,"h":118},"spriteSourceSize":{"x":0,"y":0,"w":70,"h":118},"rotated":false,"trimmed":false},"pirate_mast_g_pirate_mast_g_64_l_4_6.png":{"frame":{"x":479,"y":447,"w":81,"h":153},"sourceSize":{"w":81,"h":153},"spriteSourceSize":{"x":0,"y":0,"w":81,"h":153},"rotated":false,"trimmed":false},"pirate_mast_g_pirate_mast_g_64_k_4_2.png":{"frame":{"x":858,"y":555,"w":70,"h":142},"sourceSize":{"w":70,"h":142},"spriteSourceSize":{"x":0,"y":0,"w":70,"h":142},"rotated":false,"trimmed":false},"pirate_mast_g_pirate_mast_g_64_k_0_4.png":{"frame":{"x":435,"y":26,"w":69,"h":118},"sourceSize":{"w":69,"h":118},"spriteSourceSize":{"x":0,"y":0,"w":69,"h":118},"rotated":false,"trimmed":false},"pirate_mast_g_pirate_mast_g_64_b_0_0.png":{"frame":{"x":224,"y":494,"w":64,"h":528},"sourceSize":{"w":64,"h":528},"spriteSourceSize":{"x":0,"y":0,"w":64,"h":528},"rotated":false,"trimmed":false},"pirate_mast_g_pirate_mast_g_64_k_0_5.png":{"frame":{"x":506,"y":26,"w":69,"h":118},"sourceSize":{"w":69,"h":118},"spriteSourceSize":{"x":0,"y":0,"w":69,"h":118},"rotated":false,"trimmed":false},"pirate_mast_g_pirate_mast_g_64_l_0_0.png":{"frame":{"x":716,"y":278,"w":81,"h":130},"sourceSize":{"w":81,"h":130},"spriteSourceSize":{"x":0,"y":0,"w":81,"h":130},"rotated":false,"trimmed":false},"pirate_mast_g_pirate_mast_g_64_k_4_3.png":{"frame":{"x":882,"y":267,"w":70,"h":141},"sourceSize":{"w":70,"h":141},"spriteSourceSize":{"x":0,"y":0,"w":70,"h":141},"rotated":false,"trimmed":false},"pirate_mast_g_pirate_mast_g_64_l_4_7.png":{"frame":{"x":281,"y":21,"w":81,"h":154},"sourceSize":{"w":81,"h":154},"spriteSourceSize":{"x":0,"y":0,"w":81,"h":154},"rotated":false,"trimmed":false},"pirate_mast_g_pirate_mast_g_64_g_4_0.png":{"frame":{"x":2,"y":482,"w":76,"h":540},"sourceSize":{"w":76,"h":540},"spriteSourceSize":{"x":0,"y":0,"w":76,"h":540},"rotated":false,"trimmed":false},"pirate_mast_g_pirate_mast_g_64_h_4_0.png":{"frame":{"x":290,"y":591,"w":103,"h":431},"sourceSize":{"w":103,"h":431},"spriteSourceSize":{"x":0,"y":0,"w":103,"h":431},"rotated":false,"trimmed":false},"pirate_mast_g_pirate_mast_g_64_e_4_0.png":{"frame":{"x":930,"y":542,"w":12,"h":155},"sourceSize":{"w":12,"h":155},"spriteSourceSize":{"x":0,"y":0,"w":12,"h":155},"rotated":false,"trimmed":false},"pirate_mast_g_pirate_mast_g_64_k_0_0.png":{"frame":{"x":720,"y":26,"w":70,"h":118},"sourceSize":{"w":70,"h":118},"spriteSourceSize":{"x":0,"y":0,"w":70,"h":118},"rotated":false,"trimmed":false},"pirate_mast_g_pirate_mast_g_64_j_4_0.png":{"frame":{"x":375,"y":422,"w":18,"h":167},"sourceSize":{"w":18,"h":167},"spriteSourceSize":{"x":0,"y":0,"w":18,"h":167},"rotated":false,"trimmed":false},"pirate_mast_g_pirate_mast_g_64_k_0_6.png":{"frame":{"x":645,"y":221,"w":69,"h":118},"sourceSize":{"w":69,"h":118},"spriteSourceSize":{"x":0,"y":0,"w":69,"h":118},"rotated":false,"trimmed":false},"pirate_mast_g_pirate_mast_g_64_l_0_1.png":{"frame":{"x":562,"y":328,"w":81,"h":130},"sourceSize":{"w":81,"h":130},"spriteSourceSize":{"x":0,"y":0,"w":81,"h":130},"rotated":false,"trimmed":false},"pirate_mast_g_pirate_mast_g_64_k_4_4.png":{"frame":{"x":799,"y":401,"w":69,"h":140},"sourceSize":{"w":69,"h":140},"spriteSourceSize":{"x":0,"y":0,"w":69,"h":140},"rotated":false,"trimmed":false},"pirate_mast_g_pirate_mast_g_64_l_4_0.png":{"frame":{"x":198,"y":10,"w":81,"h":156},"sourceSize":{"w":81,"h":156},"spriteSourceSize":{"x":0,"y":0,"w":81,"h":156},"rotated":false,"trimmed":false},"pirate_mast_g_pirate_mast_g_64_i_0_0.png":{"frame":{"x":944,"y":697,"w":43,"h":325},"sourceSize":{"w":43,"h":325},"spriteSourceSize":{"x":0,"y":0,"w":43,"h":325},"rotated":false,"trimmed":false},"pirate_mast_g_pirate_mast_g_64_c_4_0.png":{"frame":{"x":395,"y":602,"w":97,"h":420},"sourceSize":{"w":97,"h":420},"spriteSourceSize":{"x":0,"y":0,"w":97,"h":420},"rotated":false,"trimmed":false},"pirate_mast_g_pirate_mast_g_64_l_0_2.png":{"frame":{"x":716,"y":410,"w":81,"h":130},"sourceSize":{"w":81,"h":130},"spriteSourceSize":{"x":0,"y":0,"w":81,"h":130},"rotated":false,"trimmed":false},"pirate_mast_g_pirate_mast_g_64_k_0_7.png":{"frame":{"x":364,"y":26,"w":69,"h":118},"sourceSize":{"w":69,"h":118},"spriteSourceSize":{"x":0,"y":0,"w":69,"h":118},"rotated":false,"trimmed":false},"pirate_mast_g_pirate_mast_g_64_a_4_0.png":{"frame":{"x":824,"y":699,"w":118,"h":323},"sourceSize":{"w":118,"h":323},"spriteSourceSize":{"x":0,"y":0,"w":118,"h":323},"rotated":false,"trimmed":false},"pirate_mast_g_pirate_mast_g_64_g_0_0.png":{"frame":{"x":80,"y":484,"w":76,"h":538},"sourceSize":{"w":76,"h":538},"spriteSourceSize":{"x":0,"y":0,"w":76,"h":538},"rotated":false,"trimmed":false},"pirate_mast_g_pirate_mast_g_64_k_4_5.png":{"frame":{"x":256,"y":177,"w":69,"h":139},"sourceSize":{"w":69,"h":139},"spriteSourceSize":{"x":0,"y":0,"w":69,"h":139},"rotated":false,"trimmed":false},"pirate_mast_g_pirate_mast_g_64_c_0_0.png":{"frame":{"x":599,"y":630,"w":97,"h":392},"sourceSize":{"w":97,"h":392},"spriteSourceSize":{"x":0,"y":0,"w":97,"h":392},"rotated":false,"trimmed":false},"pirate_mast_g_pirate_mast_g_64_e_0_0.png":{"frame":{"x":168,"y":2,"w":28,"h":164},"sourceSize":{"w":28,"h":164},"spriteSourceSize":{"x":0,"y":0,"w":28,"h":164},"rotated":false,"trimmed":false},"pirate_mast_g_pirate_mast_g_64_l_0_3.png":{"frame":{"x":882,"y":135,"w":81,"h":130},"sourceSize":{"w":81,"h":130},"spriteSourceSize":{"x":0,"y":0,"w":81,"h":130},"rotated":false,"trimmed":false},"pirate_mast_g_pirate_mast_g_64_l_4_1.png":{"frame":{"x":292,"y":435,"w":81,"h":154},"sourceSize":{"w":81,"h":154},"spriteSourceSize":{"x":0,"y":0,"w":81,"h":154},"rotated":false,"trimmed":false},"pirate_mast_g_pirate_mast_g_64_k_4_6.png":{"frame":{"x":645,"y":341,"w":69,"h":141},"sourceSize":{"w":69,"h":141},"spriteSourceSize":{"x":0,"y":0,"w":69,"h":141},"rotated":false,"trimmed":false},"pirate_mast_g_pirate_mast_g_64_l_0_4.png":{"frame":{"x":870,"y":410,"w":81,"h":130},"sourceSize":{"w":81,"h":130},"spriteSourceSize":{"x":0,"y":0,"w":81,"h":130},"rotated":false,"trimmed":false},"pirate_mast_g_pirate_mast_g_64_l_4_2.png":{"frame":{"x":395,"y":447,"w":82,"h":153},"sourceSize":{"w":82,"h":153},"spriteSourceSize":{"x":0,"y":0,"w":82,"h":153},"rotated":false,"trimmed":false},"pirate_mast_g_pirate_mast_g_64_l_4_3.png":{"frame":{"x":562,"y":460,"w":81,"h":152},"sourceSize":{"w":81,"h":152},"spriteSourceSize":{"x":0,"y":0,"w":81,"h":152},"rotated":false,"trimmed":false},"pirate_mast_g_pirate_mast_g_64_k_4_7.png":{"frame":{"x":787,"y":543,"w":69,"h":142},"sourceSize":{"w":69,"h":142},"spriteSourceSize":{"x":0,"y":0,"w":69,"h":142},"rotated":false,"trimmed":false},"pirate_mast_g_pirate_mast_g_64_a_0_0.png":{"frame":{"x":113,"y":168,"w":103,"h":314},"sourceSize":{"w":103,"h":314},"spriteSourceSize":{"x":0,"y":0,"w":103,"h":314},"rotated":false,"trimmed":false},"pirate_mast_g_pirate_mast_g_64_f_4_0.png":{"frame":{"x":698,"y":687,"w":124,"h":335},"sourceSize":{"w":124,"h":335},"spriteSourceSize":{"x":0,"y":0,"w":124,"h":335},"rotated":false,"trimmed":false},"pirate_mast_g_pirate_mast_g_64_k_0_1.png":{"frame":{"x":792,"y":17,"w":70,"h":118},"sourceSize":{"w":70,"h":118},"spriteSourceSize":{"x":0,"y":0,"w":70,"h":118},"rotated":false,"trimmed":false},"pirate_mast_g_pirate_mast_g_64_l_4_4.png":{"frame":{"x":85,"y":2,"w":81,"h":151},"sourceSize":{"w":81,"h":151},"spriteSourceSize":{"x":0,"y":0,"w":81,"h":151},"rotated":false,"trimmed":false},"pirate_mast_g_pirate_mast_g_64_i_4_0.png":{"frame":{"x":989,"y":703,"w":33,"h":319},"sourceSize":{"w":33,"h":319},"spriteSourceSize":{"x":0,"y":0,"w":33,"h":319},"rotated":false,"trimmed":false},"pirate_mast_g_pirate_mast_g_64_l_0_5.png":{"frame":{"x":799,"y":137,"w":81,"h":130},"sourceSize":{"w":81,"h":130},"spriteSourceSize":{"x":0,"y":0,"w":81,"h":130},"rotated":false,"trimmed":false},"pirate_mast_g_pirate_mast_g_64_d_4_0.png":{"frame":{"x":989,"y":394,"w":33,"h":307},"sourceSize":{"w":33,"h":307},"spriteSourceSize":{"x":0,"y":0,"w":33,"h":307},"rotated":false,"trimmed":false},"pirate_mast_g_pirate_mast_g_64_j_0_0.png":{"frame":{"x":256,"y":318,"w":34,"h":174},"sourceSize":{"w":34,"h":174},"spriteSourceSize":{"x":0,"y":0,"w":34,"h":174},"rotated":false,"trimmed":false},"pirate_mast_g_pirate_mast_g_64_b_4_0.png":{"frame":{"x":158,"y":494,"w":64,"h":528},"sourceSize":{"w":64,"h":528},"spriteSourceSize":{"x":0,"y":0,"w":64,"h":528},"rotated":false,"trimmed":false},"pirate_mast_g_pirate_mast_g_64_k_0_2.png":{"frame":{"x":577,"y":26,"w":69,"h":118},"sourceSize":{"w":69,"h":118},"spriteSourceSize":{"x":0,"y":0,"w":69,"h":118},"rotated":false,"trimmed":false},"pirate_mast_g_pirate_mast_g_64_l_4_5.png":{"frame":{"x":2,"y":2,"w":81,"h":151},"sourceSize":{"w":81,"h":151},"spriteSourceSize":{"x":0,"y":0,"w":81,"h":151},"rotated":false,"trimmed":false},"pirate_mast_g_pirate_mast_g_64_k_4_0.png":{"frame":{"x":645,"y":484,"w":69,"h":144},"sourceSize":{"w":69,"h":144},"spriteSourceSize":{"x":0,"y":0,"w":69,"h":144},"rotated":false,"trimmed":false},"pirate_mast_g_pirate_mast_g_64_h_0_0.png":{"frame":{"x":494,"y":614,"w":103,"h":408},"sourceSize":{"w":103,"h":408},"spriteSourceSize":{"x":0,"y":0,"w":103,"h":408},"rotated":false,"trimmed":false},"pirate_mast_g_pirate_mast_g_64_l_0_6.png":{"frame":{"x":716,"y":146,"w":81,"h":130},"sourceSize":{"w":81,"h":130},"spriteSourceSize":{"x":0,"y":0,"w":81,"h":130},"rotated":false,"trimmed":false},"pirate_mast_g_pirate_mast_g_64_l_0_7.png":{"frame":{"x":799,"y":269,"w":81,"h":130},"sourceSize":{"w":81,"h":130},"spriteSourceSize":{"x":0,"y":0,"w":81,"h":130},"rotated":false,"trimmed":false},"pirate_mast_g_pirate_mast_g_64_k_4_1.png":{"frame":{"x":716,"y":542,"w":69,"h":143},"sourceSize":{"w":69,"h":143},"spriteSourceSize":{"x":0,"y":0,"w":69,"h":143},"rotated":false,"trimmed":false},"pirate_mast_g_pirate_mast_g_64_f_0_0.png":{"frame":{"x":2,"y":155,"w":109,"h":325},"sourceSize":{"w":109,"h":325},"spriteSourceSize":{"x":0,"y":0,"w":109,"h":325},"rotated":false,"trimmed":false}}}