{"type":"furniture","name":"easter_c18_glassbrickcnr","visualizationType":"furniture_static","logicType":"furniture_basic","spritesheet":"easter_c18_glassbrickcnr_spritesheet.json","dimensions":{"x":1.0,"y":1.0,"z":1.0},"directions":[0,90,180,270],"assets":{"easter_c18_glassbrickcnr_64_a_6_0":{"x":24,"y":178},"easter_c18_glassbrickcnr_64_a_4_0":{"x":26,"y":178},"easter_c18_glassbrickcnr_64_a_2_0":{"x":-6,"y":178},"easter_c18_glassbrickcnr_icon_a":{"x":6,"y":14},"easter_c18_glassbrickcnr_64_a_0_0":{"x":19,"y":163}},"visualization":{"layerCount":1,"angle":45,"directions":{"0":{},"2":{},"4":{},"6":{}}}}