{"type":"furniture","name":"LTD_fashionistaf","visualizationType":"furniture_animated","logicType":"furniture_multistate","spritesheet":"LTD_fashionistaf_spritesheet.json","dimensions":{"x":1.0,"y":1.0,"z":1.0},"directions":[180,90],"assets":{"LTD_fashionistaf_64_c_4_0":{"x":32,"y":31},"LTD_fashionistaf_64_c_2_0":{"source":"LTD_fashionistaf_64_c_4_0","x":32,"y":31,"flipH":true},"LTD_fashionistaf_64_d_4_5":{"x":15,"y":83},"LTD_fashionistaf_64_d_2_7":{"source":"LTD_fashionistaf_64_d_4_7","x":4,"y":77,"flipH":true},"LTD_fashionistaf_64_d_4_4":{"x":15,"y":83},"LTD_fashionistaf_64_d_2_6":{"source":"LTD_fashionistaf_64_d_4_6","x":14,"y":82,"flipH":true},"LTD_fashionistaf_64_d_4_3":{"x":14,"y":83},"LTD_fashionistaf_64_d_2_5":{"source":"LTD_fashionistaf_64_d_4_5","x":15,"y":83,"flipH":true},"LTD_fashionistaf_64_d_4_2":{"x":14,"y":83},"LTD_fashionistaf_64_d_2_4":{"source":"LTD_fashionistaf_64_d_4_4","x":15,"y":83,"flipH":true},"LTD_fashionistaf_64_d_4_9":{"x":3,"y":40},"LTD_fashionistaf_64_d_4_8":{"x":4,"y":76},"LTD_fashionistaf_64_d_4_7":{"x":4,"y":77},"LTD_fashionistaf_64_d_2_9":{"source":"LTD_fashionistaf_64_d_4_9","x":3,"y":40,"flipH":true},"LTD_fashionistaf_64_d_4_6":{"x":14,"y":82},"LTD_fashionistaf_64_d_2_8":{"source":"LTD_fashionistaf_64_d_4_8","x":4,"y":76,"flipH":true},"LTD_fashionistaf_64_d_4_1":{"source":"LTD_fashionistaf_32_d_4_9","x":13,"y":81},"LTD_fashionistaf_64_d_2_3":{"source":"LTD_fashionistaf_64_d_4_3","x":14,"y":83,"flipH":true},"LTD_fashionistaf_64_d_4_0":{"x":33,"y":6},"LTD_fashionistaf_64_d_2_2":{"source":"LTD_fashionistaf_64_d_4_2","x":14,"y":83,"flipH":true},"LTD_fashionistaf_64_d_2_1":{"source":"LTD_fashionistaf_32_d_4_9","x":13,"y":81,"flipH":true},"LTD_fashionistaf_64_d_2_0":{"source":"LTD_fashionistaf_64_d_4_0","x":33,"y":6,"flipH":true},"LTD_fashionistaf_icon_a":{"x":8,"y":14},"LTD_fashionistaf_64_b_4_0":{"x":41,"y":75},"LTD_fashionistaf_64_b_2_0":{"source":"LTD_fashionistaf_64_b_4_0","x":41,"y":75,"flipH":true},"LTD_fashionistaf_64_a_2_0":{"source":"LTD_fashionistaf_64_a_4_0","x":36,"y":95,"flipH":true},"LTD_fashionistaf_64_a_4_0":{"x":36,"y":95}},"visualization":{"layerCount":4,"angle":45,"layers":{"0":{"ink":"COPY"},"1":{"ink":"ADD"},"2":{},"3":{}},"directions":{"2":{},"4":{}},"animations":{"0":{"layers":{"1":{"frameSequences":{"0":{"frames":{"0":{"id":1}}}}}}},"1":{"layers":{"1":{"frameSequences":{"0":{"frames":{"0":{"id":0}}}}},"3":{"loopCount":0,"frameSequences":{"0":{"frames":{"0":{"id":0},"1":{"id":0},"2":{"id":0},"3":{"id":0},"4":{"id":0},"5":{"id":0},"6":{"id":0},"7":{"id":0},"8":{"id":1},"9":{"id":1},"10":{"id":1},"11":{"id":2},"12":{"id":2},"13":{"id":2},"14":{"id":3},"15":{"id":3},"16":{"id":3},"17":{"id":4},"18":{"id":4},"19":{"id":4},"20":{"id":5},"21":{"id":5},"22":{"id":5},"23":{"id":6},"24":{"id":6},"25":{"id":6},"26":{"id":7},"27":{"id":7},"28":{"id":7},"29":{"id":8},"30":{"id":8},"31":{"id":8},"32":{"id":9},"33":{"id":9},"34":{"id":9}}}}}}}}}}