{"meta":{"app":"FFConverter ~ Joopie","format":"RGBA8888","image":"st_uni_poster.png","scale":"1.0","size":{"w":64,"h":256},"version":"1.0"},"frames":{"st_uni_poster_st_uni_poster_64_a_4_0.png":{"frame":{"x":2,"y":2,"w":35,"h":102},"sourceSize":{"w":35,"h":102},"spriteSourceSize":{"x":0,"y":0,"w":35,"h":102},"rotated":false,"trimmed":false},"st_uni_poster_st_uni_poster_64_a_2_0.png":{"frame":{"x":2,"y":106,"w":35,"h":102},"sourceSize":{"w":35,"h":102},"spriteSourceSize":{"x":0,"y":0,"w":35,"h":102},"rotated":false,"trimmed":false},"st_uni_poster_st_uni_poster_icon_a.png":{"frame":{"x":39,"y":184,"w":11,"h":24},"sourceSize":{"w":11,"h":24},"spriteSourceSize":{"x":0,"y":0,"w":11,"h":24},"rotated":false,"trimmed":false}}}