{"meta":{"app":"FFConverter ~ Joopie","format":"RGBA8888","image":"xmas_c18_starrybg.png","scale":"1.0","size":{"w":256,"h":1024},"version":"1.0"},"frames":{"xmas_c18_starrybg_xmas_c18_starrybg_64_e_4_6.png":{"frame":{"x":70,"y":354,"w":15,"h":85},"sourceSize":{"w":15,"h":85},"spriteSourceSize":{"x":0,"y":0,"w":15,"h":85},"rotated":false,"trimmed":false},"xmas_c18_starrybg_xmas_c18_starrybg_64_a_4_2.png":{"frame":{"x":70,"y":669,"w":66,"h":353},"sourceSize":{"w":66,"h":353},"spriteSourceSize":{"x":0,"y":0,"w":66,"h":353},"rotated":false,"trimmed":false},"xmas_c18_starrybg_xmas_c18_starrybg_64_b_4_2.png":{"frame":{"x":59,"y":233,"w":6,"h":6},"sourceSize":{"w":6,"h":6},"spriteSourceSize":{"x":0,"y":0,"w":6,"h":6},"rotated":false,"trimmed":false},"xmas_c18_starrybg_xmas_c18_starrybg_64_e_4_1.png":{"frame":{"x":138,"y":687,"w":1,"h":22},"sourceSize":{"w":1,"h":22},"spriteSourceSize":{"x":0,"y":0,"w":1,"h":22},"rotated":false,"trimmed":false},"xmas_c18_starrybg_xmas_c18_starrybg_64_d_4_1.png":{"frame":{"x":138,"y":796,"w":55,"h":226},"sourceSize":{"w":55,"h":226},"spriteSourceSize":{"x":0,"y":0,"w":55,"h":226},"rotated":false,"trimmed":false},"xmas_c18_starrybg_xmas_c18_starrybg_64_e_4_12.png":{"frame":{"x":152,"y":709,"w":44,"h":41},"sourceSize":{"w":44,"h":41},"spriteSourceSize":{"x":0,"y":0,"w":44,"h":41},"rotated":false,"trimmed":false},"xmas_c18_starrybg_xmas_c18_starrybg_64_c_4_1.png":{"frame":{"x":127,"y":604,"w":3,"h":3},"sourceSize":{"w":3,"h":3},"spriteSourceSize":{"x":0,"y":0,"w":3,"h":3},"rotated":false,"trimmed":false},"xmas_c18_starrybg_xmas_c18_starrybg_64_b_4_1.png":{"frame":{"x":243,"y":842,"w":4,"h":4},"sourceSize":{"w":4,"h":4},"spriteSourceSize":{"x":0,"y":0,"w":4,"h":4},"rotated":false,"trimmed":false},"xmas_c18_starrybg_xmas_c18_starrybg_64_f_4_6.png":{"frame":{"x":2,"y":2,"w":37,"h":12},"sourceSize":{"w":37,"h":12},"spriteSourceSize":{"x":0,"y":0,"w":37,"h":12},"rotated":false,"trimmed":false},"xmas_c18_starrybg_xmas_c18_starrybg_64_b_4_3.png":{"frame":{"x":244,"y":1012,"w":10,"h":10},"sourceSize":{"w":10,"h":10},"spriteSourceSize":{"x":0,"y":0,"w":10,"h":10},"rotated":false,"trimmed":false},"xmas_c18_starrybg_xmas_c18_starrybg_64_e_4_2.png":{"frame":{"x":108,"y":398,"w":3,"h":41},"sourceSize":{"w":3,"h":41},"spriteSourceSize":{"x":0,"y":0,"w":3,"h":41},"rotated":false,"trimmed":false},"xmas_c18_starrybg_xmas_c18_starrybg_64_f_4_9.png":{"frame":{"x":195,"y":805,"w":14,"h":6},"sourceSize":{"w":14,"h":6},"spriteSourceSize":{"x":0,"y":0,"w":14,"h":6},"rotated":false,"trimmed":false},"xmas_c18_starrybg_xmas_c18_starrybg_64_e_4_11.png":{"frame":{"x":152,"y":752,"w":43,"h":42},"sourceSize":{"w":43,"h":42},"spriteSourceSize":{"x":0,"y":0,"w":43,"h":42},"rotated":false,"trimmed":false},"xmas_c18_starrybg_xmas_c18_starrybg_64_e_4_5.png":{"frame":{"x":138,"y":711,"w":12,"h":83},"sourceSize":{"w":12,"h":83},"spriteSourceSize":{"x":0,"y":0,"w":12,"h":83},"rotated":false,"trimmed":false},"xmas_c18_starrybg_xmas_c18_starrybg_64_e_4_10.png":{"frame":{"x":195,"y":889,"w":47,"h":133},"sourceSize":{"w":47,"h":133},"spriteSourceSize":{"x":0,"y":0,"w":47,"h":133},"rotated":false,"trimmed":false},"xmas_c18_starrybg_xmas_c18_starrybg_64_d_4_2.png":{"frame":{"x":70,"y":441,"w":55,"h":226},"sourceSize":{"w":55,"h":226},"spriteSourceSize":{"x":0,"y":0,"w":55,"h":226},"rotated":false,"trimmed":false},"xmas_c18_starrybg_xmas_c18_starrybg_64_f_4_5.png":{"frame":{"x":214,"y":874,"w":40,"h":13},"sourceSize":{"w":40,"h":13},"spriteSourceSize":{"x":0,"y":0,"w":40,"h":13},"rotated":false,"trimmed":false},"xmas_c18_starrybg_xmas_c18_starrybg_64_f_4_1.png":{"frame":{"x":35,"y":81,"w":12,"h":3},"sourceSize":{"w":12,"h":3},"spriteSourceSize":{"x":0,"y":0,"w":12,"h":3},"rotated":false,"trimmed":false},"xmas_c18_starrybg_xmas_c18_starrybg_64_c_4_2.png":{"frame":{"x":249,"y":853,"w":5,"h":5},"sourceSize":{"w":5,"h":5},"spriteSourceSize":{"x":0,"y":0,"w":5,"h":5},"rotated":false,"trimmed":false},"xmas_c18_starrybg_xmas_c18_starrybg_64_c_4_4.png":{"frame":{"x":195,"y":796,"w":7,"h":7},"sourceSize":{"w":7,"h":7},"spriteSourceSize":{"x":0,"y":0,"w":7,"h":7},"rotated":false,"trimmed":false},"xmas_c18_starrybg_xmas_c18_starrybg_64_f_4_8.png":{"frame":{"x":214,"y":827,"w":25,"h":9},"sourceSize":{"w":25,"h":9},"spriteSourceSize":{"x":0,"y":0,"w":25,"h":9},"rotated":false,"trimmed":false},"xmas_c18_starrybg_xmas_c18_starrybg_64_a_4_0.png":{"frame":{"x":2,"y":314,"w":66,"h":353},"sourceSize":{"w":66,"h":353},"spriteSourceSize":{"x":0,"y":0,"w":66,"h":353},"rotated":false,"trimmed":false},"xmas_c18_starrybg_xmas_c18_starrybg_64_b_4_4.png":{"frame":{"x":244,"y":1000,"w":10,"h":10},"sourceSize":{"w":10,"h":10},"spriteSourceSize":{"x":0,"y":0,"w":10,"h":10},"rotated":false,"trimmed":false},"xmas_c18_starrybg_xmas_c18_starrybg_64_e_4_8.png":{"frame":{"x":87,"y":370,"w":19,"h":69},"sourceSize":{"w":19,"h":69},"spriteSourceSize":{"x":0,"y":0,"w":19,"h":69},"rotated":false,"trimmed":false},"xmas_c18_starrybg_xmas_c18_starrybg_64_e_4_4.png":{"frame":{"x":59,"y":241,"w":9,"h":71},"sourceSize":{"w":9,"h":71},"spriteSourceSize":{"x":0,"y":0,"w":9,"h":71},"rotated":false,"trimmed":false},"xmas_c18_starrybg_xmas_c18_starrybg_64_e_4_9.png":{"frame":{"x":2,"y":16,"w":31,"h":68},"sourceSize":{"w":31,"h":68},"spriteSourceSize":{"x":0,"y":0,"w":31,"h":68},"rotated":false,"trimmed":false},"xmas_c18_starrybg_xmas_c18_starrybg_64_d_4_3.png":{"frame":{"x":2,"y":86,"w":55,"h":226},"sourceSize":{"w":55,"h":226},"spriteSourceSize":{"x":0,"y":0,"w":55,"h":226},"rotated":false,"trimmed":false},"xmas_c18_starrybg_xmas_c18_starrybg_icon_a.png":{"frame":{"x":70,"y":320,"w":14,"h":32},"sourceSize":{"w":14,"h":32},"spriteSourceSize":{"x":0,"y":0,"w":14,"h":32},"rotated":false,"trimmed":false},"xmas_c18_starrybg_xmas_c18_starrybg_64_c_4_3.png":{"frame":{"x":249,"y":846,"w":5,"h":5},"sourceSize":{"w":5,"h":5},"spriteSourceSize":{"x":0,"y":0,"w":5,"h":5},"rotated":false,"trimmed":false},"xmas_c18_starrybg_xmas_c18_starrybg_64_f_4_4.png":{"frame":{"x":214,"y":848,"w":33,"h":10},"sourceSize":{"w":33,"h":10},"spriteSourceSize":{"x":0,"y":0,"w":33,"h":10},"rotated":false,"trimmed":false},"xmas_c18_starrybg_xmas_c18_starrybg_64_f_4_2.png":{"frame":{"x":87,"y":363,"w":19,"h":5},"sourceSize":{"w":19,"h":5},"spriteSourceSize":{"x":0,"y":0,"w":19,"h":5},"rotated":false,"trimmed":false},"xmas_c18_starrybg_xmas_c18_starrybg_64_a_4_1.png":{"frame":{"x":2,"y":669,"w":66,"h":353},"sourceSize":{"w":66,"h":353},"spriteSourceSize":{"x":0,"y":0,"w":66,"h":353},"rotated":false,"trimmed":false},"xmas_c18_starrybg_xmas_c18_starrybg_64_f_4_7.png":{"frame":{"x":214,"y":860,"w":36,"h":12},"sourceSize":{"w":36,"h":12},"spriteSourceSize":{"x":0,"y":0,"w":36,"h":12},"rotated":false,"trimmed":false},"xmas_c18_starrybg_xmas_c18_starrybg_64_d_4_0.png":{"frame":{"x":135,"y":666,"w":1,"h":1},"sourceSize":{"w":1,"h":1},"spriteSourceSize":{"x":0,"y":0,"w":1,"h":1},"rotated":false,"trimmed":false},"xmas_c18_starrybg_xmas_c18_starrybg_64_e_4_7.png":{"frame":{"x":195,"y":813,"w":17,"h":74},"sourceSize":{"w":17,"h":74},"spriteSourceSize":{"x":0,"y":0,"w":17,"h":74},"rotated":false,"trimmed":false},"xmas_c18_starrybg_xmas_c18_starrybg_64_e_4_3.png":{"frame":{"x":127,"y":609,"w":6,"h":58},"sourceSize":{"w":6,"h":58},"spriteSourceSize":{"x":0,"y":0,"w":6,"h":58},"rotated":false,"trimmed":false},"xmas_c18_starrybg_xmas_c18_starrybg_64_f_4_3.png":{"frame":{"x":214,"y":838,"w":27,"h":8},"sourceSize":{"w":27,"h":8},"spriteSourceSize":{"x":0,"y":0,"w":27,"h":8},"rotated":false,"trimmed":false}}}