{"type":"furniture","name":"xmas_c18_snowballpit","visualizationType":"furniture_animated","logicType":"furniture_multistate","spritesheet":"xmas_c18_snowballpit_spritesheet.json","dimensions":{"x":3.0,"y":3.0,"z":0.2},"directions":[0,90],"assets":{"xmas_c18_snowballpit_64_o_0_0":{"x":63,"y":-11},"xmas_c18_snowballpit_64_sd_0_0":{"x":96,"y":15},"xmas_c18_snowballpit_64_o_2_0":{"source":"xmas_c18_snowballpit_64_o_0_0","x":63,"y":-11,"flipH":true},"xmas_c18_snowballpit_64_sd_2_0":{"source":"xmas_c18_snowballpit_64_sd_0_0","x":96,"y":15,"flipH":true},"xmas_c18_snowballpit_64_e_2_0":{"source":"xmas_c18_snowballpit_64_e_0_0","x":3,"y":-51,"flipH":true},"xmas_c18_snowballpit_64_p_2_0":{"source":"xmas_c18_snowballpit_64_p_0_1","x":13,"y":-20,"flipH":true},"xmas_c18_snowballpit_64_p_2_1":{"source":"xmas_c18_snowballpit_64_p_0_1","x":12,"y":-20,"flipH":true},"xmas_c18_snowballpit_64_e_0_0":{"x":3,"y":-51},"xmas_c18_snowballpit_64_p_0_0":{"source":"xmas_c18_snowballpit_64_p_0_1","x":13,"y":-20},"xmas_c18_snowballpit_64_p_0_1":{"x":12,"y":-20},"xmas_c18_snowballpit_64_q_0_0":{"x":63,"y":-7},"xmas_c18_snowballpit_64_q_2_0":{"source":"xmas_c18_snowballpit_64_q_0_0","x":63,"y":-7,"flipH":true},"xmas_c18_snowballpit_64_d_0_0":{"source":"xmas_c18_snowballpit_64_e_0_0","x":33,"y":-10},"xmas_c18_snowballpit_64_d_2_0":{"source":"xmas_c18_snowballpit_64_e_0_0","x":33,"y":-10,"flipH":true},"xmas_c18_snowballpit_64_h_2_0":{"source":"xmas_c18_snowballpit_64_h_0_1","x":-9,"y":17,"flipH":true},"xmas_c18_snowballpit_64_h_2_1":{"source":"xmas_c18_snowballpit_64_h_0_1","x":-8,"y":17,"flipH":true},"xmas_c18_snowballpit_64_h_0_0":{"source":"xmas_c18_snowballpit_64_h_0_1","x":-9,"y":17},"xmas_c18_snowballpit_64_h_0_1":{"x":-8,"y":17},"xmas_c18_snowballpit_64_m_0_0":{"x":96,"y":8},"xmas_c18_snowballpit_64_m_2_0":{"source":"xmas_c18_snowballpit_64_m_0_0","x":96,"y":8,"flipH":true},"xmas_c18_snowballpit_64_n_0_0":{"x":76,"y":-12},"xmas_c18_snowballpit_64_n_0_1":{"x":77,"y":-12},"xmas_c18_snowballpit_64_g_2_0":{"source":"xmas_c18_snowballpit_64_g_0_0","x":13,"y":21,"flipH":true},"xmas_c18_snowballpit_64_g_0_0":{"x":13,"y":21},"xmas_c18_snowballpit_64_n_2_0":{"source":"xmas_c18_snowballpit_64_n_0_0","x":76,"y":-12,"flipH":true},"xmas_c18_snowballpit_64_n_2_1":{"source":"xmas_c18_snowballpit_64_n_0_1","x":77,"y":-12,"flipH":true},"xmas_c18_snowballpit_64_f_0_0":{"x":25,"y":47},"xmas_c18_snowballpit_64_f_2_0":{"source":"xmas_c18_snowballpit_64_f_0_0","x":25,"y":47,"flipH":true},"xmas_c18_snowballpit_64_j_0_0":{"x":60,"y":11},"xmas_c18_snowballpit_64_k_0_1":{"x":15,"y":3},"xmas_c18_snowballpit_64_k_2_0":{"source":"xmas_c18_snowballpit_64_k_0_0","x":16,"y":3,"flipH":true},"xmas_c18_snowballpit_64_k_2_1":{"source":"xmas_c18_snowballpit_64_k_0_1","x":15,"y":3,"flipH":true},"xmas_c18_snowballpit_64_a_2_0":{"source":"xmas_c18_snowballpit_64_a_0_0","x":31,"y":56,"flipH":true},"xmas_c18_snowballpit_64_t_2_0":{"source":"xmas_c18_snowballpit_64_t_0_0","x":31,"y":-37,"flipH":true},"xmas_c18_snowballpit_64_a_0_0":{"x":31,"y":56},"xmas_c18_snowballpit_64_t_0_0":{"x":31,"y":-37},"xmas_c18_snowballpit_64_i_0_0":{"x":51,"y":20},"xmas_c18_snowballpit_64_i_2_0":{"source":"xmas_c18_snowballpit_64_i_0_0","x":51,"y":20,"flipH":true},"xmas_c18_snowballpit_64_l_2_0":{"source":"xmas_c18_snowballpit_64_l_0_0","x":77,"y":13,"flipH":true},"xmas_c18_snowballpit_64_l_0_0":{"x":77,"y":13},"xmas_c18_snowballpit_64_c_0_0":{"x":87,"y":30},"xmas_c18_snowballpit_icon_a":{"x":14,"y":10},"xmas_c18_snowballpit_64_r_2_1":{"source":"xmas_c18_snowballpit_64_h_0_1","x":-1,"y":-33,"flipH":true},"xmas_c18_snowballpit_64_r_2_0":{"source":"xmas_c18_snowballpit_64_h_0_1","x":-2,"y":-33,"flipH":true},"xmas_c18_snowballpit_64_r_0_0":{"source":"xmas_c18_snowballpit_64_h_0_1","x":-2,"y":-33},"xmas_c18_snowballpit_64_r_0_1":{"source":"xmas_c18_snowballpit_64_h_0_1","x":-1,"y":-33},"xmas_c18_snowballpit_64_c_2_0":{"source":"xmas_c18_snowballpit_64_c_0_0","x":87,"y":30,"flipH":true},"xmas_c18_snowballpit_64_s_2_0":{"source":"xmas_c18_snowballpit_64_s_0_0","x":31,"y":-27,"flipH":true},"xmas_c18_snowballpit_64_b_2_0":{"source":"xmas_c18_snowballpit_64_b_0_0","x":65,"y":54,"flipH":true},"xmas_c18_snowballpit_64_k_0_0":{"x":16,"y":3},"xmas_c18_snowballpit_64_j_2_0":{"source":"xmas_c18_snowballpit_64_j_0_0","x":60,"y":11,"flipH":true},"xmas_c18_snowballpit_64_s_0_0":{"x":31,"y":-27},"xmas_c18_snowballpit_64_b_0_0":{"x":65,"y":54}},"visualization":{"layerCount":20,"angle":45,"layers":{"0":{},"1":{"z":1000.0},"2":{"z":2000.0},"3":{"z":3000.0},"4":{"z":4000.0},"5":{},"6":{"z":500.0},"7":{"z":500.0},"8":{"z":1000.0},"9":{"z":1500.0},"10":{"z":1500.0},"11":{"z":2000.0},"12":{"z":2500.0},"13":{"z":2500.0},"14":{"z":3000.0},"15":{"z":3500.0},"16":{"z":3500.0},"17":{"z":3500.0},"18":{"z":3990.0},"19":{"z":4500.0}},"directions":{"0":{},"2":{}},"animations":{"0":{"layers":{}},"1":{"layers":{}}}}}